pgparagraph/__init__.py
pgparagraph/_modifiers.py
pgparagraph/_pgparagraph.py
pgparagraph/_richtext.py
pgparagraph-1.0.dist-info/LICENSE
pgparagraph-1.0.dist-info/METADATA
pgparagraph-1.0.dist-info/WHEEL
pgparagraph-1.0.dist-info/top_level.txt
pgparagraph-1.0.dist-info/RECORD
